{"week":12,"title":"Linux Server เบื้องต้น","topic":"Linux Server Introduction (Ubuntu)","description":"ติดตั้ง Ubuntu Server และทำความรู้จักกับ Linux CLI","learningObjectives":["ติดตั้ง Ubuntu Server ได้","ใช้คำสั่ง Linux พื้นฐานได้","จัดการไฟล์และโฟลเดอร์ด้วย CLI ได้","อธิบายโครงสร้าง Linux File System ได้"],"slides":[{"id":"w12-s1","type":"cover","title":"Linux Server เบื้องต้น","subtitle":"Ubuntu Server 22.04 LTS","tag":"สัปดาห์ที่ 12","body":"","speakerNotes":"ยินดีต้อนรับสู่โลก Linux! ครึ่งหลังของเทอมจะเน้น Linux เป็นหลัก"},{"id":"w12-s2","type":"content","title":"ทำไมต้องเรียน Linux?","tag":"Why Linux","items":["90%+ ของ Server ทั่วโลกใช้ Linux","Cloud Server (AWS, GCP, Azure) ส่วนใหญ่รัน Linux","ฟรี Open Source ไม่มีค่าลิขสิทธิ์","เสถียร ปลอดภัย ทำงาน 24/7 ได้หลายปีไม่ต้อง Reboot","ทักษะ Linux Admin เป็นที่ต้องการในตลาดแรงงาน IT"],"speakerNotes":"แสดงสถิติจาก W3Techs ว่า Linux ครอง Server Market Share มากที่สุด"},{"id":"w12-s3","type":"content","title":"คำสั่ง Linux พื้นฐาน","tag":"Essential Commands","items":["ls — แสดงรายการไฟล์","cd /path — เปลี่ยนไดเรกทอรี","pwd — แสดงตำแหน่งปัจจุบัน","mkdir, rmdir — สร้าง/ลบ Directory","cp, mv, rm — คัดลอก/ย้าย/ลบ ไฟล์","cat, nano, vim — ดู/แก้ไขไฟล์","sudo — รันคำสั่งด้วยสิทธิ์ root"],"speakerNotes":"ให้นักเรียนพิมพ์ตามทีละคำสั่ง ห้ามคัดลอก ต้องพิมพ์เอง"},{"id":"w12-s4","type":"lab","title":"Lab 12 — ติดตั้ง Ubuntu Server","tag":"Hands-on Lab","duration":"4 ชั่วโมง","objectives":["ติดตั้ง Ubuntu Server 22.04 บน VM","Login ด้วย SSH","ใช้คำสั่งพื้นฐาน 10 คำสั่ง","สำรวจ File System"],"steps":["VirtualBox → New VM → Ubuntu Server (2GB RAM, 20GB Disk)","Mount Ubuntu Server 22.04 ISO → Install","ตั้ง Username/Password → เสร็จสิ้นติดตั้ง","Login → ลองคำสั่ง: ls, pwd, cd, mkdir, cat","สร้างโฟลเดอร์: mkdir /home/student/lab12","สร้างไฟล์: echo 'Hello Linux!' > hello.txt","ดูไฟล์: cat hello.txt","สำรวจ: ls -la /, ls -la /etc, ls -la /home"],"speakerNotes":"เน้นว่า Linux ใช้ / ไม่ใช่ \\ ตัวอักษรเล็ก-ใหญ่ต่างกัน (Case-sensitive)"},{"id":"w12-s5","type":"summary","title":"สรุปสัปดาห์ที่ 12","tag":"Week Summary","items":["✅ Linux ครอง 90%+ Server Market","✅ Ubuntu Server ฟรี เสถียร Cloud-ready","✅ คำสั่งพื้นฐาน: ls, cd, mkdir, cp, mv, rm, cat","📝 ส่ง Lab: Screenshot คำสั่ง 10 คำสั่ง","📚 สัปดาห์หน้า: Linux CLI ขั้นสูงและ Package Management"],"speakerNotes":"ท้าทาย: ใครสร้าง Folder Structure 3 ชั้นด้วย CLI ได้เร็วที่สุด?"}]}
